gunicorn_logger/__init__.py
gunicorn_logger/config.py
gunicorn_logger/filters.py
gunicorn_json_logger-0.1.0.dist-info/LICENSE
gunicorn_json_logger-0.1.0.dist-info/METADATA
gunicorn_json_logger-0.1.0.dist-info/WHEEL
gunicorn_json_logger-0.1.0.dist-info/top_level.txt
gunicorn_json_logger-0.1.0.dist-info/RECORD
