Metadata-Version: 2.1
Name: gunicorn-json-logger
Version: 0.1.0
Summary: Json log configuration for Gunicorn+Uvicorn
Home-page: https://github.com/wahlandcase/gunicorn-json-logger/
Author: Melvin Koh
Author-email: melvinkcx@gmail.com
License: MIT
Platform: UNKNOWN
Classifier: Development Status :: 3 - Alpha
Classifier: Intended Audience :: Developers
Classifier: License :: OSI Approved :: BSD License
Classifier: Operating System :: OS Independent
Classifier: Programming Language :: Python
Classifier: Programming Language :: Python :: 3
Classifier: Programming Language :: Python :: 3.6
Classifier: Programming Language :: Python :: 3.7
Classifier: Programming Language :: Python :: 3.8
Classifier: Topic :: System :: Logging
Requires-Python: >=3.6
License-File: LICENSE
Requires-Dist: python-json-logger (>=2.0)
